fastremap/__init__.py
fastremap/fastremap.cpython-310-x86_64-linux-gnu.so
fastremap/fastremap.pxd
fastremap/fastremap.pyi
fastremap/fastremap.pyx
fastremap/ipt.hpp
fastremap/py.typed
fastremap/ska_flat_hash_map.hpp
fastremap-1.17.7.dist-info/METADATA
fastremap-1.17.7.dist-info/WHEEL
fastremap-1.17.7.dist-info/pbr.json
fastremap-1.17.7.dist-info/top_level.txt
fastremap-1.17.7.dist-info/RECORD
fastremap-1.17.7.dist-info/licenses/AUTHORS
fastremap-1.17.7.dist-info/licenses/LICENSE
