Metadata-Version: 2.4
Name: fastremap
Version: 1.17.7
Summary: Remap, mask, renumber, unique, and in-place transposition of 3D labeled images. Point cloud too.
Home-page: https://github.com/seung-lab/fastremap/
Author: William Silversmith
Author-email: ws9@princeton.edu
Classifier: Intended Audience :: Developers
Classifier: Development Status :: 5 - Production/Stable
Classifier: Programming Language :: Python
Classifier: Programming Language :: Python :: 3
Classifier: Programming Language :: Python :: 3.9
Classifier: Programming Language :: Python :: 3.10
Classifier: Programming Language :: Python :: 3.11
Classifier: Programming Language :: Python :: 3.12
Classifier: Programming Language :: Python :: 3.13
Classifier: Topic :: Utilities
Requires-Python: >=3.9,<4.0
License-File: LICENSE
License-File: AUTHORS
Requires-Dist: numpy
Dynamic: author
Dynamic: author-email
Dynamic: classifier
Dynamic: description
Dynamic: description-content-type
Dynamic: home-page
Dynamic: license-file
Dynamic: requires-dist
Dynamic: requires-python
Dynamic: summary
